{
  "type": "FeatureCollection",
  "name": "Fiesta Island fishing-structure & caution",
  "features": [
    {
      "type": "Feature",
      "properties": {
        "name": "Rocky bottom (reported)",
        "kind": "Structure",
        "notes": "Rocky bottom along the bank — typical structure that holds bass and croaker. Work the edges on a moving tide, especially low light."
      },
      "geometry": {
        "type": "Point",
        "coordinates": [
          -117.2285924,
          32.7887964
        ]
      }
    }
  ]
}
